[
    {
        "archived": true,
        "author": "kn0thing",
        "author_flair_background_color": null,
        "author_flair_css_class": null,
        "author_flair_richtext": [
        
        ],
        "author_flair_text": null,
        "author_flair_text_color": null,
        "author_flair_type": "text",
        "brand_safe": true,
        "can_gild": true,
        "contest_mode": false,
        "created_utc": 1119552233,
        "distinguished": null,
        "domain": "downingstreetmemo.com",
        "edited": false,
        "gilded": 6,
        "hidden": false,
        "hide_score": false,
        "id": "87",
        "is_crosspostable": true,
        "is_reddit_media_domain": false,
        "is_self": false,
        "is_video": false,
        "link_flair_css_class": null,
        "link_flair_richtext": [
        
        ],
        "link_flair_text": null,
        "link_flair_text_color": "dark",
        "link_flair_type": "text",
        "locked": false,
        "media": null,
        "media_embed": {
        
        },
        "no_follow": false,
        "num_comments": 390,
        "num_crossposts": 0,
        "over_18": false,
        "parent_whitelist_status": "all_ads",
        "permalink": "\/r\/reddit.com\/comments\/87\/the_downing_street_memo\/",
        "rte_mode": "markdown",
        "score": 183,
        "secure_media": null,
        "secure_media_embed": {
        
        },
        "selftext": "",
        "send_replies": true,
        "spoiler": false,
        "stickied": false,
        "subreddit": "reddit.com",
        "subreddit_id": "t5_6",
        "subreddit_name_prefixed": "r\/reddit.com",
        "subreddit_type": "archived",
        "suggested_sort": null,
        "thumbnail": "default",
        "thumbnail_height": null,
        "thumbnail_width": null,
        "title": "The Downing Street Memo",
        "url": "http:\/\/www.downingstreetmemo.com",
        "whitelist_status": "all_ads"
    },
    {
        "archived": true,
        "author": "spez",
        "author_flair_background_color": null,
        "author_flair_css_class": null,
        "author_flair_richtext": [
        
        ],
        "author_flair_text": null,
        "author_flair_text_color": null,
        "author_flair_type": "text",
        "brand_safe": true,
        "can_gild": true,
        "contest_mode": false,
        "created_utc": 1119552314,
        "distinguished": null,
        "domain": "online.wsj.com",
        "edited": false,
        "gilded": 1,
        "hidden": false,
        "hide_score": false,
        "id": "88",
        "is_crosspostable": true,
        "is_reddit_media_domain": false,
        "is_self": false,
        "is_video": false,
        "link_flair_css_class": null,
        "link_flair_richtext": [
        
        ],
        "link_flair_text": null,
        "link_flair_text_color": "dark",
        "link_flair_type": "text",
        "locked": false,
        "media": null,
        "media_embed": {
        
        },
        "no_follow": false,
        "num_comments": 1,
        "num_crossposts": 0,
        "over_18": false,
        "parent_whitelist_status": "all_ads",
        "permalink": "\/r\/reddit.com\/comments\/88\/marketers_scan_blogs_for_brand_insights\/",
        "post_hint": "link",
        "preview": {
        "enabled": false,
        "images": [
            {
            "id": "sY0KabKBfGX1bB1IJMqbQ2uVGR8YGeFaRCkpwuSQc80",
            "resolutions": [
                {
                "height": 108,
                "url": "https:\/\/i.redditmedia.com\/3AaqtMW3S2tWA6KTKe2XhM1WHVEdVap3ZH7vvc6l0aA.jpg?fit=crop&amp;crop=faces%2Centropy&amp;arh=2&amp;w=108&amp;s=3e2fdc8f6741028a5bf278d18cfd187e",
                "width": 108
                }
            ],
            "source": {
                "height": 180,
                "url": "https:\/\/i.redditmedia.com\/3AaqtMW3S2tWA6KTKe2XhM1WHVEdVap3ZH7vvc6l0aA.jpg?s=42ede1f6317643a1eeef675eef594d35",
                "width": 180
            },
            "variants": {
                
            }
            }
        ]
        },
        "rte_mode": "markdown",
        "score": 8,
        "secure_media": null,
        "secure_media_embed": {
        
        },
        "selftext": "",
        "send_replies": true,
        "spoiler": false,
        "stickied": false,
        "subreddit": "reddit.com",
        "subreddit_id": "t5_6",
        "subreddit_name_prefixed": "r\/reddit.com",
        "subreddit_type": "archived",
        "suggested_sort": null,
        "thumbnail": "https:\/\/b.thumbs.redditmedia.com\/6xZDlx-ZGehhnHeytqbBeJD6f15leHnjT5LZ5vmiF8I.jpg",
        "thumbnail_height": 140,
        "thumbnail_width": 140,
        "title": "Marketers Scan Blogs For Brand Insights",
        "url": "http:\/\/online.wsj.com\/public\/article\/0,,SB111948406207267049-_s5eff_5SbJW3B_RdxwYLvU3s6c_20050723,00.html?mod=blogs",
        "whitelist_status": "all_ads"
    },
    {
        "archived": true,
        "author": "kn0thing",
        "author_flair_background_color": null,
        "author_flair_css_class": null,
        "author_flair_richtext": [
        
        ],
        "author_flair_text": null,
        "author_flair_text_color": null,
        "author_flair_type": "text",
        "brand_safe": true,
        "can_gild": true,
        "contest_mode": false,
        "created_utc": 1119552369,
        "distinguished": null,
        "domain": "paulgraham.com",
        "edited": false,
        "gilded": 0,
        "hidden": false,
        "hide_score": false,
        "id": "89",
        "is_crosspostable": true,
        "is_reddit_media_domain": false,
        "is_self": false,
        "is_video": false,
        "link_flair_css_class": null,
        "link_flair_richtext": [
        
        ],
        "link_flair_text": null,
        "link_flair_text_color": "dark",
        "link_flair_type": "text",
        "locked": false,
        "media": null,
        "media_embed": {
        
        },
        "no_follow": false,
        "num_comments": 4,
        "num_crossposts": 0,
        "over_18": false,
        "parent_whitelist_status": "all_ads",
        "permalink": "\/r\/reddit.com\/comments\/89\/why_nerds_are_unpopular\/",
        "rte_mode": "markdown",
        "score": 26,
        "secure_media": null,
        "secure_media_embed": {
        
        },
        "selftext": "",
        "send_replies": true,
        "spoiler": false,
        "stickied": false,
        "subreddit": "reddit.com",
        "subreddit_id": "t5_6",
        "subreddit_name_prefixed": "r\/reddit.com",
        "subreddit_type": "archived",
        "suggested_sort": null,
        "thumbnail": "default",
        "thumbnail_height": null,
        "thumbnail_width": null,
        "title": "Why Nerds are Unpopular",
        "url": "http:\/\/www.paulgraham.com\/nerds.html",
        "whitelist_status": "all_ads"
    },
    {
        "archived": true,
        "author": "kn0thing",
        "author_flair_background_color": null,
        "author_flair_css_class": null,
        "author_flair_richtext": [
        
        ],
        "author_flair_text": null,
        "author_flair_text_color": null,
        "author_flair_type": "text",
        "brand_safe": true,
        "can_gild": true,
        "contest_mode": false,
        "created_utc": 1119552453,
        "distinguished": null,
        "domain": "macrumors.com",
        "edited": false,
        "gilded": 0,
        "hidden": false,
        "hide_score": false,
        "id": "90",
        "is_crosspostable": true,
        "is_reddit_media_domain": false,
        "is_self": false,
        "is_video": false,
        "link_flair_css_class": null,
        "link_flair_richtext": [
        
        ],
        "link_flair_text": null,
        "link_flair_text_color": "dark",
        "link_flair_type": "text",
        "locked": false,
        "media": null,
        "media_embed": {
        
        },
        "no_follow": true,
        "num_comments": 1,
        "num_crossposts": 0,
        "over_18": false,
        "parent_whitelist_status": "all_ads",
        "permalink": "\/r\/reddit.com\/comments\/90\/mac_rumors_first_developer_intel_macs_photos\/",
        "rte_mode": "markdown",
        "score": 2,
        "secure_media": null,
        "secure_media_embed": {
        
        },
        "selftext": "",
        "send_replies": true,
        "spoiler": false,
        "stickied": false,
        "subreddit": "reddit.com",
        "subreddit_id": "t5_6",
        "subreddit_name_prefixed": "r\/reddit.com",
        "subreddit_type": "archived",
        "suggested_sort": null,
        "thumbnail": "default",
        "thumbnail_height": null,
        "thumbnail_width": null,
        "title": "Mac Rumors: First Developer Intel Macs (Photos)",
        "url": "http:\/\/www.macrumors.com\/pages\/2005\/06\/20050622183807.shtml",
        "whitelist_status": "all_ads"
    },
    {
        "archived": true,
        "author": "chickenlittle",
        "author_flair_background_color": null,
        "author_flair_css_class": null,
        "author_flair_richtext": [
        
        ],
        "author_flair_text": null,
        "author_flair_text_color": null,
        "author_flair_type": "text",
        "brand_safe": true,
        "can_gild": true,
        "contest_mode": false,
        "created_utc": 1119552602,
        "distinguished": null,
        "domain": "wired.com",
        "edited": false,
        "gilded": 0,
        "hidden": false,
        "hide_score": false,
        "id": "91",
        "is_crosspostable": true,
        "is_reddit_media_domain": false,
        "is_self": false,
        "is_video": false,
        "link_flair_css_class": null,
        "link_flair_richtext": [
        
        ],
        "link_flair_text": null,
        "link_flair_text_color": "dark",
        "link_flair_type": "text",
        "locked": false,
        "media": null,
        "media_embed": {
        
        },
        "no_follow": false,
        "num_comments": 2,
        "num_crossposts": 0,
        "over_18": false,
        "parent_whitelist_status": "all_ads",
        "permalink": "\/r\/reddit.com\/comments\/91\/wired_news_beware_the_google_threat\/",
        "rte_mode": "markdown",
        "score": 10,
        "secure_media": null,
        "secure_media_embed": {
        
        },
        "selftext": "",
        "send_replies": true,
        "spoiler": false,
        "stickied": false,
        "subreddit": "reddit.com",
        "subreddit_id": "t5_6",
        "subreddit_name_prefixed": "r\/reddit.com",
        "subreddit_type": "archived",
        "suggested_sort": null,
        "thumbnail": "default",
        "thumbnail_height": null,
        "thumbnail_width": null,
        "title": "Wired News: Beware the Google Threat",
        "url": "http:\/\/www.wired.com\/news\/culture\/0,1284,67982,00.html?tw=wn_tophead_4",
        "whitelist_status": "all_ads"
    },
    {
        "archived": true,
        "author": "agentOrange",
        "author_flair_background_color": null,
        "author_flair_css_class": null,
        "author_flair_richtext": [
        
        ],
        "author_flair_text": null,
        "author_flair_text_color": null,
        "author_flair_type": "text",
        "brand_safe": true,
        "can_gild": true,
        "contest_mode": false,
        "created_utc": 1119552659,
        "distinguished": null,
        "domain": "washingtonpost.com",
        "edited": false,
        "gilded": 0,
        "hidden": false,
        "hide_score": false,
        "id": "92",
        "is_crosspostable": true,
        "is_reddit_media_domain": false,
        "is_self": false,
        "is_video": false,
        "link_flair_css_class": null,
        "link_flair_richtext": [
        
        ],
        "link_flair_text": null,
        "link_flair_text_color": "dark",
        "link_flair_type": "text",
        "locked": false,
        "media": null,
        "media_embed": {
        
        },
        "no_follow": false,
        "num_comments": 0,
        "num_crossposts": 0,
        "over_18": false,
        "parent_whitelist_status": "all_ads",
        "permalink": "\/r\/reddit.com\/comments\/92\/rumsfeld_will_not_set_timetable_for_iraq\/",
        "post_hint": "link",
        "preview": {
        "enabled": false,
        "images": [
            {
            "id": "Hyozig2bWZ_kSAiekssggE7pZUZC88Lg21XQvuvN984",
            "resolutions": [
                
            ],
            "source": {
                "height": 50,
                "url": "https:\/\/i.redditmedia.com\/rG2Tau9yggB4G6a1s_w4JKfkaiwMlBZucQPOXesZyGA.jpg?s=f8514d8f8395535996abf33215aaf6f3",
                "width": 50
            },
            "variants": {
                
            }
            }
        ]
        },
        "rte_mode": "markdown",
        "score": 10,
        "secure_media": null,
        "secure_media_embed": {
        
        },
        "selftext": "",
        "send_replies": true,
        "spoiler": false,
        "stickied": false,
        "subreddit": "reddit.com",
        "subreddit_id": "t5_6",
        "subreddit_name_prefixed": "r\/reddit.com",
        "subreddit_type": "archived",
        "suggested_sort": null,
        "thumbnail": "https:\/\/b.thumbs.redditmedia.com\/IX6maGBYJXBaQx8cNIbZM61IU_HDkBaTcd5_6VwuJOk.jpg",
        "thumbnail_height": 50,
        "thumbnail_width": 50,
        "title": "Rumsfeld Will Not Set Timetable for Iraq Withdrawal",
        "url": "http:\/\/www.washingtonpost.com\/wp-dyn\/content\/article\/2005\/06\/23\/AR2005062300242.html?sub=AR",
        "whitelist_status": "all_ads"
    },
    {
        "archived": true,
        "author": "[deleted]",
        "author_flair_background_color": "",
        "author_flair_css_class": null,
        "author_flair_text": null,
        "author_flair_text_color": "dark",
        "brand_safe": true,
        "can_gild": false,
        "contest_mode": false,
        "created_utc": 1119552820,
        "distinguished": null,
        "domain": "newscientistspace.com",
        "edited": false,
        "gilded": 0,
        "hidden": false,
        "hide_score": false,
        "id": "93",
        "is_crosspostable": false,
        "is_reddit_media_domain": false,
        "is_self": false,
        "is_video": false,
        "link_flair_css_class": null,
        "link_flair_richtext": [
        
        ],
        "link_flair_text": null,
        "link_flair_text_color": "dark",
        "link_flair_type": "text",
        "locked": false,
        "media": null,
        "media_embed": {
        
        },
        "no_follow": true,
        "num_comments": 4,
        "num_crossposts": 0,
        "over_18": false,
        "parent_whitelist_status": "all_ads",
        "permalink": "\/r\/reddit.com\/comments\/93\/new_scientist_space_breaking_news_failure_of\/",
        "rte_mode": "markdown",
        "score": 0,
        "secure_media": null,
        "secure_media_embed": {
        
        },
        "selftext": "[deleted]",
        "send_replies": true,
        "spoiler": false,
        "stickied": false,
        "subreddit": "reddit.com",
        "subreddit_id": "t5_6",
        "subreddit_name_prefixed": "r\/reddit.com",
        "subreddit_type": "archived",
        "suggested_sort": null,
        "thumbnail": "default",
        "thumbnail_height": null,
        "thumbnail_width": null,
        "title": "New Scientist SPACE - Breaking News - Failure of solar sail mission virtually certain",
        "url": "http:\/\/www.newscientistspace.com\/article.ns?id=dn7568",
        "whitelist_status": "all_ads"
    },
    {
        "archived": true,
        "author": "Col. Klobb",
        "author_flair_background_color": null,
        "author_flair_css_class": null,
        "author_flair_richtext": [
        
        ],
        "author_flair_text": null,
        "author_flair_text_color": null,
        "author_flair_type": "text",
        "brand_safe": true,
        "can_gild": true,
        "contest_mode": false,
        "created_utc": 1119552850,
        "distinguished": null,
        "domain": "newscientist.com",
        "edited": false,
        "gilded": 0,
        "hidden": false,
        "hide_score": false,
        "id": "94",
        "is_crosspostable": true,
        "is_reddit_media_domain": false,
        "is_self": false,
        "is_video": false,
        "link_flair_css_class": null,
        "link_flair_richtext": [
        
        ],
        "link_flair_text": null,
        "link_flair_text_color": "dark",
        "link_flair_type": "text",
        "locked": false,
        "media": null,
        "media_embed": {
        
        },
        "no_follow": true,
        "num_comments": 0,
        "num_crossposts": 0,
        "over_18": false,
        "parent_whitelist_status": "all_ads",
        "permalink": "\/r\/reddit.com\/comments\/94\/new_scientist_news_do_games_prime_brain_for\/",
        "rte_mode": "markdown",
        "score": 3,
        "secure_media": null,
        "secure_media_embed": {
        
        },
        "selftext": "",
        "send_replies": true,
        "spoiler": false,
        "stickied": false,
        "subreddit": "reddit.com",
        "subreddit_id": "t5_6",
        "subreddit_name_prefixed": "r\/reddit.com",
        "subreddit_type": "archived",
        "suggested_sort": null,
        "thumbnail": "default",
        "thumbnail_height": null,
        "thumbnail_width": null,
        "title": "New Scientist News - Do games prime brain for violence?",
        "url": "http:\/\/www.newscientist.com\/article.ns?id=mg18625053.200",
        "whitelist_status": "all_ads"
    },
    {
        "archived": true,
        "author": "MaDMaX2",
        "author_flair_background_color": null,
        "author_flair_css_class": null,
        "author_flair_richtext": [
        
        ],
        "author_flair_text": null,
        "author_flair_text_color": null,
        "author_flair_type": "text",
        "brand_safe": true,
        "can_gild": true,
        "contest_mode": false,
        "created_utc": 1119552944,
        "distinguished": null,
        "domain": "cnn.com",
        "edited": false,
        "gilded": 0,
        "hidden": false,
        "hide_score": false,
        "id": "95",
        "is_crosspostable": true,
        "is_reddit_media_domain": false,
        "is_self": false,
        "is_video": false,
        "link_flair_css_class": null,
        "link_flair_richtext": [
        
        ],
        "link_flair_text": null,
        "link_flair_text_color": "dark",
        "link_flair_type": "text",
        "locked": false,
        "media": null,
        "media_embed": {
        
        },
        "no_follow": true,
        "num_comments": 0,
        "num_crossposts": 0,
        "over_18": false,
        "parent_whitelist_status": "all_ads",
        "permalink": "\/r\/reddit.com\/comments\/95\/cnncom_un_experts_blast_us_on_guantanamo_bay_jun\/",
        "rte_mode": "markdown",
        "score": 5,
        "secure_media": null,
        "secure_media_embed": {
        
        },
        "selftext": "",
        "send_replies": true,
        "spoiler": false,
        "stickied": false,
        "subreddit": "reddit.com",
        "subreddit_id": "t5_6",
        "subreddit_name_prefixed": "r\/reddit.com",
        "subreddit_type": "archived",
        "suggested_sort": null,
        "thumbnail": "default",
        "thumbnail_height": null,
        "thumbnail_width": null,
        "title": "CNN.com - U.N. experts blast U.S. on Guantanamo Bay - Jun 23, 2005",
        "url": "http:\/\/www.cnn.com\/2005\/US\/06\/23\/un.guantanamo\/index.html",
        "whitelist_status": "all_ads"
    },
    {
        "archived": true,
        "author": "kn0thing",
        "author_flair_background_color": null,
        "author_flair_css_class": null,
        "author_flair_richtext": [
        
        ],
        "author_flair_text": null,
        "author_flair_text_color": null,
        "author_flair_type": "text",
        "brand_safe": true,
        "can_gild": true,
        "contest_mode": false,
        "created_utc": 1119553006,
        "distinguished": null,
        "domain": "news.bbc.co.uk",
        "edited": false,
        "gilded": 0,
        "hidden": false,
        "hide_score": false,
        "id": "96",
        "is_crosspostable": true,
        "is_reddit_media_domain": false,
        "is_self": false,
        "is_video": false,
        "link_flair_css_class": null,
        "link_flair_richtext": [
        
        ],
        "link_flair_text": null,
        "link_flair_text_color": "dark",
        "link_flair_type": "text",
        "locked": false,
        "media": null,
        "media_embed": {
        
        },
        "no_follow": false,
        "num_comments": 0,
        "num_crossposts": 0,
        "over_18": false,
        "parent_whitelist_status": "all_ads",
        "permalink": "\/r\/reddit.com\/comments\/96\/piracy_seen_as_normal\/",
        "post_hint": "link",
        "preview": {
        "enabled": false,
        "images": [
            {
            "id": "6PurPDfaPv8kA-gIEJczSs0sCwwylP4qtUYY8fE_FRk",
            "resolutions": [
                {
                "height": 80,
                "url": "https:\/\/i.redditmedia.com\/MwxiiQHo4eH9cNM1XejC5VbLkRJ8WgFYWKeq7lUC9ds.jpg?fit=crop&amp;crop=faces%2Centropy&amp;arh=2&amp;w=108&amp;s=d30f6bccda7b330e90b24e6b8f702282",
                "width": 108
                }
            ],
            "source": {
                "height": 152,
                "url": "https:\/\/i.redditmedia.com\/MwxiiQHo4eH9cNM1XejC5VbLkRJ8WgFYWKeq7lUC9ds.jpg?s=91f316356e944b0c68ff4da73243458e",
                "width": 203
            },
            "variants": {
                
            }
            }
        ]
        },
        "rte_mode": "markdown",
        "score": 2,
        "secure_media": null,
        "secure_media_embed": {
        
        },
        "selftext": "",
        "send_replies": true,
        "spoiler": false,
        "stickied": false,
        "subreddit": "reddit.com",
        "subreddit_id": "t5_6",
        "subreddit_name_prefixed": "r\/reddit.com",
        "subreddit_type": "archived",
        "suggested_sort": null,
        "thumbnail": "https:\/\/b.thumbs.redditmedia.com\/ZwFtxCECm1ag9Lpz1oFhH-6mDznfwaZB3ZIW1wy_7Hc.jpg",
        "thumbnail_height": 104,
        "thumbnail_width": 140,
        "title": "piracy seen as normal",
        "url": "http:\/\/news.bbc.co.uk\/1\/hi\/technology\/4122624.stm",
        "whitelist_status": "all_ads"
    },
    {
        "archived": true,
        "author": "kn0thing",
        "author_flair_background_color": null,
        "author_flair_css_class": null,
        "author_flair_richtext": [
        
        ],
        "author_flair_text": null,
        "author_flair_text_color": null,
        "author_flair_type": "text",
        "brand_safe": true,
        "can_gild": true,
        "contest_mode": false,
        "created_utc": 1119553074,
        "distinguished": null,
        "domain": "script.aculo.us",
        "edited": false,
        "gilded": 0,
        "hidden": false,
        "hide_score": false,
        "id": "97",
        "is_crosspostable": true,
        "is_reddit_media_domain": false,
        "is_self": false,
        "is_video": false,
        "link_flair_css_class": null,
        "link_flair_richtext": [
        
        ],
        "link_flair_text": null,
        "link_flair_text_color": "dark",
        "link_flair_type": "text",
        "locked": false,
        "media": null,
        "media_embed": {
        
        },
        "no_follow": true,
        "num_comments": 1,
        "num_crossposts": 0,
        "over_18": false,
        "parent_whitelist_status": "all_ads",
        "permalink": "\/r\/reddit.com\/comments\/97\/scriptaculous_web_20_javascript\/",
        "post_hint": "link",
        "preview": {
        "enabled": false,
        "images": [
            {
            "id": "HLosgc7ZnyiKteWcGS1uGwVcy_2vnXc72buMfrwRrwk",
            "resolutions": [
                {
                "height": 108,
                "url": "https:\/\/i.redditmedia.com\/U9OkMR6Ty_MpIrp7WJJFbIInfPyaD5c2CWQef2bDtVo.jpg?fit=crop&amp;crop=faces%2Centropy&amp;arh=2&amp;w=108&amp;s=82115af49c5b045ef2cf261e63b5206c",
                "width": 108
                },
                {
                "height": 216,
                "url": "https:\/\/i.redditmedia.com\/U9OkMR6Ty_MpIrp7WJJFbIInfPyaD5c2CWQef2bDtVo.jpg?fit=crop&amp;crop=faces%2Centropy&amp;arh=2&amp;w=216&amp;s=db1bfdad0a96f771fcbc253097d709d0",
                "width": 216
                }
            ],
            "source": {
                "height": 310,
                "url": "https:\/\/i.redditmedia.com\/U9OkMR6Ty_MpIrp7WJJFbIInfPyaD5c2CWQef2bDtVo.jpg?s=512eff214ea7e444f249da42d3b9749e",
                "width": 310
            },
            "variants": {
                
            }
            }
        ]
        },
        "rte_mode": "markdown",
        "score": 0,
        "secure_media": null,
        "secure_media_embed": {
        
        },
        "selftext": "",
        "send_replies": true,
        "spoiler": false,
        "stickied": false,
        "subreddit": "reddit.com",
        "subreddit_id": "t5_6",
        "subreddit_name_prefixed": "r\/reddit.com",
        "subreddit_type": "archived",
        "suggested_sort": null,
        "thumbnail": "https:\/\/b.thumbs.redditmedia.com\/msgl6wiTsZ-i-Wxgv7bokUf7MVpIJFAT9aG1W8KrSbM.jpg",
        "thumbnail_height": 140,
        "thumbnail_width": 140,
        "title": "script.aculo.us - web 2.0 javascript",
        "url": "http:\/\/script.aculo.us\/",
        "whitelist_status": "all_ads"
    }
]